{
  "productos": [
    {
      "nombre": "Jugo de Naranja",
      "precio": "300",
      "id": 3
    },
    {
      "nombre": "Rib Eye 800g",
      "precio": "200",
      "id": 4
    },
    {
      "nombre": "Jugo de Fresa",
      "precio": "200",
      "id": 5
    },
    {
      "nombre": "Urban",
      "precio": 344335,
      "id": 6
    },
    {
      "nombre": "Urban",
      "precio": 40000,
      "id": 7
    },
    {
      "nombre": "coffee",
      "precio": 350,
      "id": 8
    },
    {
      "nombre": "Urban",
      "precio": 1212,
      "id": 9
    },
    {
      "nombre": "bchgccgfc",
      "precio": 55444,
      "id": 10
    },
    {
      "nombre": "qwqwjsbjfjwdkq",
      "precio": 121212,
      "id": 11
    }
  ]
}